LICENSE.txt
MANIFEST.in
README.rst
pyproject.toml
setup.py
tutor_credentials.egg-info/PKG-INFO
tutor_credentials.egg-info/SOURCES.txt
tutor_credentials.egg-info/dependency_links.txt
tutor_credentials.egg-info/entry_points.txt
tutor_credentials.egg-info/requires.txt
tutor_credentials.egg-info/top_level.txt
tutorcredentials/__about__.py
tutorcredentials/__init__.py
tutorcredentials/plugin.py
tutorcredentials/patches/.gitignore
tutorcredentials/patches/caddyfile
tutorcredentials/patches/k8s-deployments
tutorcredentials/patches/k8s-jobs
tutorcredentials/patches/k8s-services
tutorcredentials/patches/kustomization-configmapgenerator
tutorcredentials/patches/local-docker-compose-caddy-aliases
tutorcredentials/patches/local-docker-compose-dev-services
tutorcredentials/patches/local-docker-compose-jobs-services
tutorcredentials/patches/local-docker-compose-services
tutorcredentials/patches/openedx-lms-common-settings
tutorcredentials/patches/openedx-lms-development-settings
tutorcredentials/patches/openedx-lms-production-settings
tutorcredentials/templates/credentials/apps/.gitignore
tutorcredentials/templates/credentials/apps/credentials/settings/__init__.py
tutorcredentials/templates/credentials/apps/credentials/settings/development.py
tutorcredentials/templates/credentials/apps/credentials/settings/production.py
tutorcredentials/templates/credentials/apps/credentials/settings/partials/common.py
tutorcredentials/templates/credentials/build/.gitignore
tutorcredentials/templates/credentials/build/credentials/Dockerfile
tutorcredentials/templates/credentials/build/credentials/assets.py
tutorcredentials/templates/credentials/build/credentials/requirements/private-sample.txt
tutorcredentials/templates/credentials/tasks/.gitignore
tutorcredentials/templates/credentials/tasks/credentials/build
tutorcredentials/templates/credentials/tasks/credentials/init
tutorcredentials/templates/credentials/tasks/lms/init
tutorcredentials/templates/credentials/tasks/mysql/init
tutorcredentials/templates/credentials/tasks/mysql/sync_users