Metadata-Version: 2.1
Name: tutor-credentials
Version: 19.0.0
Summary: A Tutor plugin for Open edX Credentials service
Home-page: https://github.com/overhangio/tutor-credentials.git
Author: Lawrence McDaniel
Author-email: lpm0073@gmail.com
Maintainer: Edly
Maintainer-email: faraz.maqsood@arbisoft.com
License: AGPLv3
Project-URL: Code, https://github.com/overhangio/tutor-credentials.git
Project-URL: Issue tracker, https://github.com/overhangio/tutor-credentials.git/issues
Project-URL: Community, https://discuss.overhang.io
Classifier: Development Status :: 5 - Production/Stable
Classifier: Intended Audience :: Developers
Classifier: License :: OSI Approved :: GNU Affero General Public License v3
Classifier: Operating System :: OS Independent
Classifier: Programming Language :: Python
Classifier: Programming Language :: Python :: 3.9
Classifier: Programming Language :: Python :: 3.10
Classifier: Programming Language :: Python :: 3.11
Classifier: Programming Language :: Python :: 3.12
Requires-Python: >=3.9
License-File: LICENSE.txt
Requires-Dist: tutor<20.0.0,>=19.0.0
Requires-Dist: tutor-discovery<20.0.0,>=19.0.0
Requires-Dist: tutor-mfe<20.0.0,>=19.0.0
Provides-Extra: dev
Requires-Dist: tutor[dev]<20.0.0,>=19.0.0; extra == "dev"
